mentpy/__init__.py
mentpy/calculator/__init__.py
mentpy/calculator/borrows.py
mentpy/calculator/linalg2.py
mentpy/calculator/state_ops.py
mentpy/gradients/__init__.py
mentpy/gradients/_finite_difference.py
mentpy/gradients/_parameter_shift.py
mentpy/gradients/grad.py
mentpy/mbqc/__init__.py
mentpy/mbqc/flow.py
mentpy/mbqc/mbqcircuit.py
mentpy/mbqc/templates.py
mentpy/mbqc/view.py
mentpy/mbqc/states/__init__.py
mentpy/mbqc/states/aklt.py
mentpy/mbqc/states/cluster.py
mentpy/mbqc/states/graphstate.py
mentpy/noise/__init__.py
mentpy/noise/base_noise.py
mentpy/operators/__init__.py
mentpy/operators/controlled_ment.py
mentpy/operators/gates.py
mentpy/operators/ment.py
mentpy/operators/pauliop.py
mentpy/optimizers/__init__.py
mentpy/optimizers/adam.py
mentpy/optimizers/base.py
mentpy/optimizers/bp_tools.py
mentpy/optimizers/rcd.py
mentpy/optimizers/sgd.py
mentpy/simulators/__init__.py
mentpy/simulators/base_simulator.py
mentpy/simulators/np_simulator_dm.py
mentpy/simulators/np_simulator_sv.py
mentpy/simulators/pattern_simulator.py
mentpy/simulators/pennylane_simulator.py
mentpy/utils/__init__.py
mentpy/utils/expressivity.py
mentpy/utils/flow_space.py
mentpy/utils/generate_data.py
mentpy/utils/lc_equivalence.py
mentpy/utils/lie_algebra.py
mentpy-0.1.0a15.dist-info/LICENSE
mentpy-0.1.0a15.dist-info/METADATA
mentpy-0.1.0a15.dist-info/WHEEL
mentpy-0.1.0a15.dist-info/top_level.txt
mentpy-0.1.0a15.dist-info/RECORD
