Metadata-Version: 2.1
Name: mentpy
Version: 0.1.0a15
Summary: A Python library for simulating MBQC circuits
Author-email: Luis Mantilla <contact@mentpy.com>
License: Apache-2.0
Classifier: Programming Language :: Python :: 3
Classifier: License :: OSI Approved :: Apache Software License
Requires-Python: >=3.9
License-File: LICENSE
Requires-Dist: galois >=0.3.7
Requires-Dist: matplotlib >=3.8.2
Requires-Dist: networkx >=3.2.1
Requires-Dist: numpy >=1.25.2
Requires-Dist: pathos >=0.3.1
Requires-Dist: PennyLane >=0.33.1
Requires-Dist: scikit-learn >=1.3.2
Requires-Dist: scipy >=1.11.4
Provides-Extra: dev
Requires-Dist: black >=23.12.0 ; extra == 'dev'
Requires-Dist: coverage >=7.3.4 ; extra == 'dev'
Requires-Dist: ipykernel >=6.25.2 ; extra == 'dev'
Requires-Dist: pandas >=2.1.4 ; extra == 'dev'
Requires-Dist: pickleshare >=0.7.5 ; extra == 'dev'
Requires-Dist: pyarrow >=15.0.0 ; extra == 'dev'
Requires-Dist: pytest >=7.4.2 ; extra == 'dev'
Requires-Dist: Sphinx >=7.2.6 ; extra == 'dev'
Requires-Dist: sphinx-immaterial >=0.11.10 ; extra == 'dev'
